LICENSE
README.md
setup.py
CVE_2009_0347.egg-info/PKG-INFO
CVE_2009_0347.egg-info/SOURCES.txt
CVE_2009_0347.egg-info/dependency_links.txt
CVE_2009_0347.egg-info/entry_points.txt
CVE_2009_0347.egg-info/requires.txt
CVE_2009_0347.egg-info/top_level.txt
cve20090347/main.py
cve20090347/includes/__init__.py
cve20090347/includes/bot.py
cve20090347/includes/filereader.py
cve20090347/includes/scan.py
cve20090347/includes/writefile.py
cve20090347/utils/__init__.py
cve20090347/utils/configure.py
cve20090347/utils/const.py
cve20090347/utils/helpers.py
cve20090347/utils/status.py